<?xml version="1.0" ?>
<widgets xmlns:xsi="http://www.w3.org/2001/XMLSchema-instance"
         xsi:noNamespaceSchemaLocation="urn:magento:helloworld:Magento_Widget:etc/widget.xsd">
    <widget class="Codilar\CouponModule\Block\Widget\Vendors" id="codilar_coupon_vendors">
        <label>Blog Posts</label>
        <description>Posts</description>
        <parameters>
            <parameter name="posts" sort_order="10" visible="true" required="true" xsi:type="text">
                <label>Number of Vendors to Display</label>
            </parameter>
            <parameter name="collection_sort_by" sort_order="20" visible="true" required="true" xsi:type="select"
                       source_model="Codilar\CouponModule\Model\Details\Source\SortBy">
                <label>Sort Collection By</label>
            </parameter>
            <parameter name="collection_sort_order" sort_order="20" required="true" xsi:type="select" visible="true"
                       source_model="Codilar\CouponModule\Model\Details\Source\SortOrder">
                <label translate="true">Sort Collection Order</label>
            </parameter>
        </parameters>
    </widget>
</widgets>